llama_index/py.typed
llama_index/vector_stores/opensearch/__init__.py
llama_index/vector_stores/opensearch/base.py
llama_index_vector_stores_opensearch-0.6.3.dist-info/METADATA
llama_index_vector_stores_opensearch-0.6.3.dist-info/WHEEL
llama_index_vector_stores_opensearch-0.6.3.dist-info/licenses/LICENSE
llama_index_vector_stores_opensearch-0.6.3.dist-info/RECORD
